setup.py
kershaw/__init__.py
kershaw/io.py
kershaw/lang.py
kershaw.egg-info/PKG-INFO
kershaw.egg-info/SOURCES.txt
kershaw.egg-info/dependency_links.txt
kershaw.egg-info/top_level.txt