Metadata-Version: 1.1
Name: kershaw
Version: 0.2.0
Summary: Kershaw General Purpose Utility Library
Home-page: https://github.com/SPoage/kershaw
Author: Shane Poage
Author-email: SPoage@users.noreply.github.com
License: UNKNOWN
Platform: UNKNOWN
Classifier: Development Status :: 2 - Pre-Alpha
Classifier: Environment :: Console
Classifier: Intended Audience :: Developers
Classifier: License :: OSI Approved :: IBM Public License
Classifier: Operating System :: POSIX :: Linux
Classifier: Programming Language :: Python :: 3.4
